lightsim2grid_cpp.cpython-311-x86_64-linux-gnu.so
lightsim2grid/__init__.py
lightsim2grid/contingencyAnalysis.py
lightsim2grid/lightSimBackend.py
lightsim2grid/physical_law_checker.py
lightsim2grid/securityAnalysis.py
lightsim2grid/timeSerie.py
lightsim2grid/_utils/__init__.py
lightsim2grid/compilation_options/__init__.py
lightsim2grid/elements/__init__.py
lightsim2grid/gridmodel/__init__.py
lightsim2grid/gridmodel/compare_gridmodel.py
lightsim2grid/gridmodel/from_pandapower/__init__.py
lightsim2grid/gridmodel/from_pandapower/_aux_add_dc_line.py
lightsim2grid/gridmodel/from_pandapower/_aux_add_gen.py
lightsim2grid/gridmodel/from_pandapower/_aux_add_line.py
lightsim2grid/gridmodel/from_pandapower/_aux_add_load.py
lightsim2grid/gridmodel/from_pandapower/_aux_add_sgen.py
lightsim2grid/gridmodel/from_pandapower/_aux_add_shunt.py
lightsim2grid/gridmodel/from_pandapower/_aux_add_slack.py
lightsim2grid/gridmodel/from_pandapower/_aux_add_storage.py
lightsim2grid/gridmodel/from_pandapower/_aux_add_trafo.py
lightsim2grid/gridmodel/from_pandapower/_aux_check_legit.py
lightsim2grid/gridmodel/from_pandapower/_my_const.py
lightsim2grid/gridmodel/from_pandapower/_pp_bus_to_ls_bus.py
lightsim2grid/gridmodel/from_pandapower/initGridModel.py
lightsim2grid/gridmodel/from_pypowsybl/__init__.py
lightsim2grid/gridmodel/from_pypowsybl/_aux_handle_slack.py
lightsim2grid/gridmodel/from_pypowsybl/_from_pypowsybl.py
lightsim2grid/newtonpf/__init__.py
lightsim2grid/pandapower_compat/__init__.py
lightsim2grid/pandapower_compat/dcpf/__init__.py
lightsim2grid/pandapower_compat/dcpf/_dcpf.py
lightsim2grid/pandapower_compat/newtonpf/__init__.py
lightsim2grid/pandapower_compat/newtonpf/_newtonpf.py
lightsim2grid/rewards/__init__.py
lightsim2grid/rewards/n1ContingencyReward.py
lightsim2grid/solver/__init__.py
lightsim2grid-0.12.1.dist-info/METADATA
lightsim2grid-0.12.1.dist-info/WHEEL
lightsim2grid-0.12.1.dist-info/top_level.txt
lightsim2grid-0.12.1.dist-info/RECORD
lightsim2grid-0.12.1.dist-info/licenses/AUTHORS.txt
lightsim2grid-0.12.1.dist-info/licenses/LICENSE
lightsim2grid-0.12.1.dist-info/licenses/LICENSE.md
