Metadata-Version: 2.4
Name: LightSim2Grid
Version: 0.12.1
Summary: LightSim2Grid implements a c++ backend targeting the Grid2Op platform.
Home-page: https://github.com/grid2op/lightsim2grid/
Author: Benjamin Donnot
Author-email: benjamin.donnot@rte-france.com
License: MPL 2.0
Keywords: pandapower powergrid simulator KLU Eigen c++
Platform: Windows
Platform: Linux
Platform: Mac OS-X
Platform: Unix
Classifier: Development Status :: 4 - Beta
Classifier: Programming Language :: Python :: 3.7
Classifier: Programming Language :: Python :: 3.8
Classifier: Programming Language :: Python :: 3.9
Classifier: Programming Language :: Python :: 3.10
Classifier: Programming Language :: Python :: 3.11
Classifier: Programming Language :: Python :: 3.12
Classifier: Programming Language :: Python :: 3.13
Classifier: Programming Language :: Python :: 3.14
Classifier: License :: OSI Approved :: Mozilla Public License 2.0 (MPL 2.0)
Classifier: Intended Audience :: Developers
Classifier: Intended Audience :: Education
Classifier: Intended Audience :: Science/Research
Classifier: Natural Language :: English
License-File: LICENSE
License-File: LICENSE.md
License-File: AUTHORS.txt
Requires-Dist: setuptools
Requires-Dist: pip
Requires-Dist: pybind11
Requires-Dist: scipy
Requires-Dist: numpy
Requires-Dist: packaging
Requires-Dist: typing_extensions
Provides-Extra: docs
Requires-Dist: numpydoc>=0.9.2; extra == "docs"
Requires-Dist: sphinx<7,>=2.4.4; extra == "docs"
Requires-Dist: sphinx-rtd-theme>=0.4.3; extra == "docs"
Requires-Dist: sphinxcontrib-trio>=1.1.0; extra == "docs"
Requires-Dist: autodocsumm>=0.1.13; extra == "docs"
Requires-Dist: grid2op>=1.6.4; extra == "docs"
Requires-Dist: recommonmark; extra == "docs"
Requires-Dist: pypowsybl; extra == "docs"
Provides-Extra: benchmark
Requires-Dist: tabulate; extra == "benchmark"
Requires-Dist: grid2op>=1.6.4; extra == "benchmark"
Requires-Dist: numpy>=1.20; extra == "benchmark"
Requires-Dist: distro; extra == "benchmark"
Requires-Dist: py-cpuinfo; extra == "benchmark"
Provides-Extra: recommended
Requires-Dist: grid2op>=1.6.4; extra == "recommended"
Requires-Dist: numba; extra == "recommended"
Provides-Extra: test
Requires-Dist: grid2op>=1.6.4; extra == "test"
Requires-Dist: numba; extra == "test"
Requires-Dist: pandapower>=2.14.0; extra == "test"
Requires-Dist: pypowsybl; extra == "test"
Dynamic: author
Dynamic: author-email
Dynamic: classifier
Dynamic: description
Dynamic: description-content-type
Dynamic: home-page
Dynamic: keywords
Dynamic: license
Dynamic: license-file
Dynamic: platform
Dynamic: provides-extra
Dynamic: requires-dist
Dynamic: summary
